parsion/__init__.py
parsion/core.py
parsion/exceptions.py
parsion/lex.py
parsion/parsegen.py
parsion/parser.py
parsion/self_check.py
parsion-0.0.5.dist-info/LICENSE
parsion-0.0.5.dist-info/METADATA
parsion-0.0.5.dist-info/WHEEL
parsion-0.0.5.dist-info/top_level.txt
parsion-0.0.5.dist-info/RECORD
