Metadata-Version: 2.2
Name: parsion
Version: 0.0.5
Summary: Simple LR parser generator and parser for easy integration
Author-email: Max Sikström <max@pengi.se>
License: MIT License
Project-URL: Homepage, https://github.com/pengi/parsion
Classifier: Development Status :: 4 - Beta
Classifier: Intended Audience :: Developers
Classifier: Natural Language :: English
Classifier: License :: OSI Approved :: MIT License
Classifier: Programming Language :: Python
Classifier: Programming Language :: Python :: 3
Requires-Python: >=3.9
License-File: LICENSE
